{"artworkUrl60": "https://is5-ssl.mzstatic.com/image/thumb/Purple30/v4/68/33/50/6833500d-56a2-0b42-f4d6-6af9c487b06b/source/60x60bb.jpg", "artworkUrl100": "https://is5-ssl.mzstatic.com/image/thumb/Purple30/v4/68/33/50/6833500d-56a2-0b42-f4d6-6af9c487b06b/source/100x100bb.jpg", "artistViewUrl": "https://itunes.apple.com/us/developer/red-hammer-software/id328569137?uo=4", "isGameCenterEnabled": false, "screenshotUrls": ["https://is1-ssl.mzstatic.com/image/thumb/Purple1/v4/8d/50/ea/8d50ea3c-3607-eeb0-168f-1e9ae9c4dce1/source/392x696bb.jpg", "https://is3-ssl.mzstatic.com/image/thumb/Purple3/v4/b1/ac/f5/b1acf5f3-f96c-b58c-0ee5-ca0fa6f38438/source/392x696bb.jpg", "https://is4-ssl.mzstatic.com/image/thumb/Purple1/v4/b1/de/2c/b1de2ca9-d70d-d688-e7d8-ee325807ad2d/source/392x696bb.jpg", "https://is1-ssl.mzstatic.com/image/thumb/Purple1/v4/b7/6a/c2/b76ac202-2e42-ca3b-7147-1314d1daa959/source/392x696bb.jpg", "https://is4-ssl.mzstatic.com/image/thumb/Purple3/v4/06/15/31/0615319f-30d2-8c51-2de6-1c4b9d6c6971/source/392x696bb.jpg"], "ipadScreenshotUrls": ["https://is1-ssl.mzstatic.com/image/thumb/Purple1/v4/ab/9d/c2/ab9dc24d-bf05-581f-4532-63e605f5daf8/source/480x351bb.jpg", "https://is2-ssl.mzstatic.com/image/thumb/Purple5/v4/b7/d1/a2/b7d1a275-bbac-9787-3001-dbbea27d6cf9/source/480x351bb.jpg", "https://is1-ssl.mzstatic.com/image/thumb/Purple5/v4/c3/e3/4e/c3e34e15-6ff6-f5dc-a16c-d46a6c512fc1/source/480x351bb.jpg", "https://is1-ssl.mzstatic.com/image/thumb/Purple1/v4/d5/5e/7f/d55e7f09-9c08-58b0-b48d-48e7b33a58d9/source/480x351bb.jpg", "https://is4-ssl.mzstatic.com/image/thumb/Purple3/v4/05/5a/18/055a1893-94b6-bf0c-8816-b279f82712cd/source/480x351bb.jpg"], "appletvScreenshotUrls": [], "artworkUrl512": "https://is5-ssl.mzstatic.com/image/thumb/Purple30/v4/68/33/50/6833500d-56a2-0b42-f4d6-6af9c487b06b/source/512x512bb.jpg", "supportedDevices": ["iPad2Wifi-iPad2Wifi", "iPad23G-iPad23G", "iPhone4S-iPhone4S", "iPadThirdGen-iPadThirdGen", "iPadThirdGen4G-iPadThirdGen4G", "iPhone5-iPhone5", "iPodTouchFifthGen-iPodTouchFifthGen", "iPadFourthGen-iPadFourthGen", "iPadFourthGen4G-iPadFourthGen4G", "iPadMini-iPadMini", "iPadMini4G-iPadMini4G", "iPhone5c-iPhone5c", "iPhone5s-iPhone5s", "iPadAir-iPadAir", "iPadAirCellular-iPadAirCellular", "iPadMiniRetina-iPadMiniRetina", "iPadMiniRetinaCellular-iPadMiniRetinaCellular", "iPhone6-iPhone6", "iPhone6Plus-iPhone6Plus", "iPadAir2-iPadAir2", "iPadAir2Cellular-iPadAir2Cellular", "iPadMini3-iPadMini3", "iPadMini3Cellular-iPadMini3Cellular", "iPodTouchSixthGen-iPodTouchSixthGen", "iPhone6s-iPhone6s", "iPhone6sPlus-iPhone6sPlus", "iPadMini4-iPadMini4", "iPadMini4Cellular-iPadMini4Cellular", "iPadPro-iPadPro", "iPadProCellular-iPadProCellular", "iPadPro97-iPadPro97", "iPadPro97Cellular-iPadPro97Cellular", "iPhoneSE-iPhoneSE", "iPhone7-iPhone7", "iPhone7Plus-iPhone7Plus", "iPad611-iPad611", "iPad612-iPad612", "iPad71-iPad71", "iPad72-iPad72", "iPad73-iPad73", "iPad74-iPad74", "iPhone8-iPhone8", "iPhone8Plus-iPhone8Plus", "iPhoneX-iPhoneX", "iPad75-iPad75", "iPad76-iPad76", "iPhoneXS-iPhoneXS", "iPhoneXSMax-iPhoneXSMax", "iPhoneXR-iPhoneXR", "iPad812-iPad812", "iPad834-iPad834", "iPad856-iPad856", "iPad878-iPad878"], "advisories": [], "kind": "software", "features": ["iosUniversal"], "contentAdvisoryRating": "4+", "trackViewUrl": "https://itunes.apple.com/us/app/free-relaxing-nature-sounds-and-spa-music/id345747251?mt=8&uo=4", "trackCensoredName": "Free Relaxing Nature Sounds and SPA Music", "averageUserRatingForCurrentVersion": 4.5, "languageCodesISO2A": ["EN"], "fileSizeBytes": "256460800", "sellerUrl": "http://rtstudio.net/NatureSoundsLite.html", "userRatingCountForCurrentVersion": 72, "trackContentRating": "4+", "sellerName": "Red Hammer Software", "currentVersionReleaseDate": "2016-06-28T14:35:54Z", "formattedPrice": "Free", "trackId": 345747251, "trackName": "Free Relaxing Nature Sounds and SPA Music", "genreIds": ["6013", "6012"], "releaseNotes": "* iOS 9 adaptations\n* Bug-fix for in-app purchases\n\nWe hope you enjoy this new update! \u2028 \n* * * * * Positive reviews and feedback help us keep the updates and new features coming. Thank you for your support!", "isVppDeviceBasedLicensingEnabled": true, "primaryGenreId": 6013, "primaryGenreName": "Health & Fitness", "releaseDate": "2009-12-18T08:00:00Z", "currency": "USD", "wrapperType": "software", "version": "4.7.502", "description": "As part of our worldwide promotional efforts, we offer all music and sounds from In-App Purchase Premium Collections for free. \nEvery  music pack features your favorite music CDs combined with the flexibility of iPhone/iPad applications (like a playlist or an alarm clock). All tracks have quality 192 mp3 with 44.1 MHz sample rate; several hours of relaxing and meditation music in total. And all that is for free. Any comparable CDs are about 5 to 10 dollars. Enjoy!!! \n\nMake sure to download and get several hours of  music by just installing this free app and turn your iPhone/iPad into a airplay music system!\n\nThis app has beautiful soundscapes that will help you to get away from the noise of the city, feel free from the problems that surround you and  help you fall asleep.\n\nUsing it you can:\n* Relax,\n* Reduce stress,\n* Sleep and feel better,\n* Prepare for meditation,\n* Use for spa ambiance or physiotherapy and much more.\n\nThis  is a 2 in 1 application. We put together two components in one app. Which is an audio experience with 25 beautiful nature sounds and a soundboard with 35 sounds where you can mix a number of soundtracks to have a peaceful experience.\n\nPlease see what customers have said about Relaxing Sounds of Nature:\n*****\nLove \nGreat app! Love using it to calm me down and relax.\n*****\nGreat app! \nI was a bit skeptical when I bought this. I've been having trouble sleeping for a while and couldn't find anything to help. But this put me to sleep within 10 minutes! I am amazed! :D\n*****\nRancher \nA 100% YES this is peace times ten. It works great so much to choose from. I asked you delivered, thanks.\n*****\n\nHere are the amazing features you will get with Relaxing Sounds of Nature Lite:\n* Additional downloads free and paid are available with In-App Purchase.\n\n* iPhone 4 and iPhone 4S 5x retina display support. \n\n* You can use it for relaxation, meditation, and yoga, physiotherapy, spa music etc... \n\n* The soundboard has 35 relaxing sounds with which you can combine or enjoy them on their own.  Perhaps you will choose the sounds of breaking waves with seagulls, crickets chirping or the sounds of a flute, or perhaps played all together. You can do it all and much more.\n\n* All selected sounds from the soundboard can be saved and replayed later. All you have to do is open the Soundboard and tap on any of the sounds that you would like to combine together and save them.\n\n* We know you, or your child could fall asleep to sounds of nature. So we have included 2 easy to use night timers that you can set to various time intervals to allow you to peacefully fall asleep to any of our breathtaking sounds.\n\n* Wakeup timer allows you to wake up to the sounds of nature. Just set time and your favorite soundtrack. Wakeup Timer allows selecting any sound shipped within the app.\n\n* As there is a large number of sounds, we have included the Favorites page where you can add your favorite sounds.\n\n* Completely customizable. Create your own combination from 35 possible sounds (+ 100 free downloads) save them and use later.\n\n* Every sound in the soundboard has its own volume control.\n\n* iOS 4 background audio support. Play our relaxing sounds while you're using other apps.\n\n* Digital Clock Display with amazing pictures of nature.  Use our Slideshow feature to see them one after another. \n\n* AirPlay support.  Use AirPlay to stream our sounds wirelessly from your iPhone, iPad, iPod touch to your HDTV and speakers with Apple TV or to your AirPlay speakers.\n\n* Night timers have a Fade Out feature.\n\n* Wakeup timer has a snooze feature. \n\n* It is free of charge.\n\n\nSimply, sleep well and feel better.", "minimumOsVersion": "8.0", "artistId": 328569137, "artistName": "Red Hammer Software", "genres": ["Health & Fitness", "Lifestyle"], "price": 0.0, "bundleId": "net.rhsoftware.SoundsOfNatureSoundboardLite", "averageUserRating": 4.0, "userRatingCount": 6042}